hotknots/CG_best_parameters_ISMB2007.txt
hotknots/__init__.py
hotknots/coaxial.dat
hotknots/coaxstack.dat
hotknots/hotknots.cpython-38-darwin.so
hotknots/mathews-asint1x2-dna.dat
hotknots/mathews-asint1x2-dna.dh
hotknots/mathews-dangle-dna.dat
hotknots/mathews-dangle-dna.dh
hotknots/mathews-loop-dna.dat
hotknots/mathews-loop-dna.dh
hotknots/mathews-miscloop-dna.dat
hotknots/mathews-miscloop-dna.dh
hotknots/mathews-sint2-dna.dat
hotknots/mathews-sint2-dna.dh
hotknots/mathews-sint4-dna.dat
hotknots/mathews-sint4-dna.dh
hotknots/mathews-stack-dna.dat
hotknots/mathews-stack-dna.dh
hotknots/mathews-tloop-dna.dat
hotknots/mathews-tloop-dna.dh
hotknots/mathews-triloop-dna.dat
hotknots/mathews-triloop-dna.dh
hotknots/mathews-tstackh-dna.dat
hotknots/mathews-tstackh-dna.dh
hotknots/mathews-tstacki-dna.dat
hotknots/mathews-tstacki-dna.dh
hotknots/multirnafold.conf
hotknots/parameters_CC06.txt
hotknots/parameters_CC09.txt
hotknots/parameters_DP03.txt
hotknots/parameters_DP09.txt
hotknots/pkenergy.conf
hotknots/pkmodelCC2006.dat
hotknots/pkmodelDP.dat
hotknots/pkmodelRE.dat
hotknots/tstackcoax.dat
hotknots/turner-asint1x2-rna.dat
hotknots/turner-asint1x2-rna.dg
hotknots/turner-asint1x2-rna.dh
hotknots/turner-dangle-rna.dat
hotknots/turner-dangle-rna.dg
hotknots/turner-dangle-rna.dh
hotknots/turner-loop-rna.dat
hotknots/turner-loop-rna.dg
hotknots/turner-loop-rna.dh
hotknots/turner-miscloop-rna.dat
hotknots/turner-miscloop-rna.dg
hotknots/turner-miscloop-rna.dh
hotknots/turner-sint2-rna.dat
hotknots/turner-sint2-rna.dg
hotknots/turner-sint2-rna.dh
hotknots/turner-sint4-rna.dat
hotknots/turner-sint4-rna.dg
hotknots/turner-sint4-rna.dh
hotknots/turner-stack-rna.dat
hotknots/turner-stack-rna.dg
hotknots/turner-stack-rna.dh
hotknots/turner-tloop-rna.dat
hotknots/turner-tloop-rna.dg
hotknots/turner-tloop-rna.dh
hotknots/turner-triloop-rna.dat
hotknots/turner-triloop-rna.dg
hotknots/turner-triloop-rna.dh
hotknots/turner-tstackh-rna.dat
hotknots/turner-tstackh-rna.dg
hotknots-2.4.dist-info/LICENSE
hotknots-2.4.dist-info/METADATA
hotknots-2.4.dist-info/WHEEL
hotknots-2.4.dist-info/top_level.txt
hotknots-2.4.dist-info/RECORD
