Metadata-Version: 2.1
Name: hotknots
Version: 2.4
Summary: A a tool to predict RNA secondary structure, including pseudoknots
Home-page: https://github.com/deprekate/HotKnots
Author: Katelyn McNair, Jihong Ren, Baharak Rastegari, Cristina Pop, Mirela Andronescu 
Author-email: deprekate@gmail.com
Classifier: Programming Language :: Python :: 3
Classifier: License :: OSI Approved :: GNU General Public License v3 or later (GPLv3+)
Classifier: Operating System :: OS Independent
Requires-Python: >3.5.2
License-File: LICENSE
